__init__.py
pfmgmt.py
returns.py
risks.py
finpro-0.0.1.dist-info/METADATA
finpro-0.0.1.dist-info/WHEEL
finpro-0.0.1.dist-info/licenses/LICENSE
finpro-0.0.1.dist-info/RECORD
