Metadata-Version: 2.1
Name: FinPro
Version: 0.0.1
Summary: A tool for Finance Analysis.
Project-URL: Homepage, https://github.com/JakeC021/FinPro
Project-URL: Bug Tracker, https://github.com/JakeC021/FinPro/issues
Author-email: Jake <cjake021@outlook.com>
License-File: LICENSE
Classifier: License :: OSI Approved :: MIT License
Classifier: Operating System :: OS Independent
Classifier: Programming Language :: Python :: 3
Requires-Python: >=3.7
